{"elements":[{"from":[7.428571,-6.476282,6.0189314],"to":[8.571428,0.9522891,7.1617885],"rotation":{"angle":0.0,"axis":"x","origin":[8.0,1.1428566,6.857143]},"faces":{"east":{"uv":[1.25,0.25,1.75,0.75],"rotation":0,"texture":"#0","tintindex":0},"south":{"uv":[2.25,0.25,2.75,0.75],"rotation":0,"texture":"#0","tintindex":0},"north":{"uv":[0.25,0.25,0.75,0.75],"rotation":0,"texture":"#0","tintindex":0},"west":{"uv":[3.25,0.25,3.75,0.75],"rotation":0,"texture":"#0","tintindex":0},"up":{"uv":[4.25,0.25,4.75,0.75],"rotation":0,"texture":"#0","tintindex":0},"down":{"uv":[5.25,0.25,5.75,0.75],"rotation":0,"texture":"#0","tintindex":0}}},{"from":[7.428571,0.70467854,7.1758623],"to":[8.571428,8.13325,8.31872],"rotation":{"angle":0.0,"axis":"x","origin":[8.0,8.0,8.0]},"faces":{"east":{"uv":[13.25,0.25,13.75,0.75],"rotation":0,"texture":"#0","tintindex":0},"south":{"uv":[14.25,0.25,14.75,0.75],"rotation":0,"texture":"#0","tintindex":0},"north":{"uv":[12.25,0.25,12.75,0.75],"rotation":0,"texture":"#0","tintindex":0},"west":{"uv":[15.25,0.25,15.75,0.75],"rotation":0,"texture":"#0","tintindex":0},"up":{"uv":[0.25,1.25,0.75,1.75],"rotation":0,"texture":"#0","tintindex":0},"down":{"uv":[1.25,1.25,1.75,1.75],"rotation":0,"texture":"#0","tintindex":0}}}],"textures":{"0":"modelengine:entity/texture"},"display":{"head":{"translation":[0.0,-6.4,0.0],"scale":[4.0,4.0,4.0]}}}